pagerduty_trigger
