Metadata-Version: 1.0
Name: pagerduty-trigger
Version: 1.0.1
Summary: Trigger Pagerduty alerts class
Home-page: https://github.com/gtmanfred/pagerduty_trigger/
Author: Daniel Wallace
Author-email: danielwallace@gtmanfred.com
License: UNKNOWN
Platform: UNKNOWN
